mgetool/__init__.py
mgetool/cluster.py
mgetool/draft.py
mgetool/exports.py
mgetool/jit_c_torch_load.py
mgetool/jit_c_torch_load_inline.py
mgetool/newclass.py
mgetool/packbox.py
mgetool/quick_import.py
mgetool/show.py
mgetool/tool.py
mgetool/translate_msgid.py
mgetool/tree_plot.py
mgetool/cli/__init__.py
mgetool/cli/_formatter.py
mgetool/cli/batchpy.py
mgetool/cli/cpdir.py
mgetool/cli/cptodirs.py
mgetool/cli/findpath.py
mgetool/cli/main.py
mgetool/cli/makebatch.py
mgetool/imports/__init__.py
mgetool/imports/batchfile.py
mgetool/imports/batchfilematch.py
mgetool/imports/call.py
mgetool/imports/leaf.py
mgetool-0.0.77.dist-info/METADATA
mgetool-0.0.77.dist-info/WHEEL
mgetool-0.0.77.dist-info/entry_points.txt
mgetool-0.0.77.dist-info/RECORD
