Metadata-Version: 2.4
Name: mgetool
Version: 0.0.77
Summary: This is an tool box contains tools for mgedata. Some of code are non-originality, just copy for use. All the referenced code are marked, details can be shown in their sources
Author-email: wangchangxin <986798607@qq.com>
Maintainer: wangchangxin
License: BSD-3-Clause
Keywords: draft,exports,imports,newclass,packbox,show,tool
Classifier: Development Status :: 4 - Beta
Classifier: Intended Audience :: Science/Research
Classifier: Natural Language :: English
Classifier: Operating System :: Microsoft :: Windows
Classifier: Operating System :: Unix
Classifier: Programming Language :: Python :: 3.8
Classifier: Programming Language :: Python :: 3.9
Classifier: Programming Language :: Python :: 3.10
Classifier: Programming Language :: Python :: 3.11
Classifier: Programming Language :: Python :: 3.12
Requires-Python: >=3.6
Requires-Dist: joblib
Requires-Dist: matplotlib
Requires-Dist: numpy
Requires-Dist: pandas
Requires-Dist: requests
Requires-Dist: scipy
Requires-Dist: seaborn
Requires-Dist: six
Requires-Dist: sympy
Requires-Dist: tqdm
